anomed_utils/__init__.py
anomed_utils/arrays.py
anomed_utils/web.py
anomed_utils-0.3.8.dist-info/METADATA
anomed_utils-0.3.8.dist-info/WHEEL
anomed_utils-0.3.8.dist-info/licenses/LICENSE
anomed_utils-0.3.8.dist-info/RECORD
