Metadata-Version: 2.4
Name: anomed-utils
Version: 0.3.8
Summary: Basic web and array utilities useful for contributing to the AnoMed platform.
Author-email: Yannik Potdevin <ypo.uzl@proton.me>
Maintainer-email: Yannik Potdevin <ypo.uzl@proton.me>
License: MIT License
License-File: LICENSE
Classifier: Development Status :: 1 - Planning
Classifier: Intended Audience :: Developers
Requires-Python: >=3.10
Requires-Dist: falcon~=4.0
Requires-Dist: filelock~=3.16
Requires-Dist: numpy~=1.26
Requires-Dist: pandas~=2.2
Requires-Dist: pyarrow~=19.0
Requires-Dist: requests~=2.32
Requires-Dist: urllib3~=2.3
Provides-Extra: dev
Requires-Dist: ruff~=0.7; extra == 'dev'
Provides-Extra: test
Requires-Dist: coverage~=7.6; extra == 'test'
Requires-Dist: pytest-cov~=6.0; extra == 'test'
Requires-Dist: pytest-mock~=3.14; extra == 'test'
Requires-Dist: pytest~=8.3; extra == 'test'
